imgcompare/__init__.py
imgcompare/imgcompare.py
imgcompare-1.0.1.dist-info/LICENSE.txt
imgcompare-1.0.1.dist-info/METADATA
imgcompare-1.0.1.dist-info/WHEEL
imgcompare-1.0.1.dist-info/top_level.txt
imgcompare-1.0.1.dist-info/RECORD
