Metadata-Version: 2.1
Name: imgcompare
Version: 1.0.1
Summary: compares two images for equality or a difference percentage
Home-page: https://github.com/datenhahn/imgcompare
Author: Jonas Hahn
Author-email: jonas.hahn@datenhahn.de
License: MIT
Download-URL: https://github.com/datenhahn/imgcompare/tarball/1.0.1
Project-URL: Source, https://github.com/datenhahn/imgcompare
Project-URL: Documentation, https://github.com/datenhahn/imgcompare
Project-URL: Tracker, https://github.com/datenhahn/imgcompare/issues
Keywords: image,compare
Platform: UNKNOWN
Classifier: Development Status :: 5 - Production/Stable
Classifier: Intended Audience :: Developers
Classifier: License :: OSI Approved :: MIT License
Classifier: Programming Language :: Python :: 2.6
Classifier: Programming Language :: Python :: 2.7
Requires-Python: >=2.6, <3
Requires-Dist: pillow (<7)
